{
  "recentFiles": [
    {
      "basename": "Instant Pot Fried Rice",
      "path": "Databases/Recipes/Instant Pot Fried Rice.md"
    },
    {
      "basename": "People",
      "path": "Templates/People.md"
    },
    {
      "basename": "Jane Doe",
      "path": "Databases/CRM/Jane Doe.md"
    },
    {
      "basename": "John Doe",
      "path": "Databases/CRM/John Doe.md"
    },
    {
      "basename": "Quarterly",
      "path": "Templates/Quarterly.md"
    },
    {
      "basename": "CRM",
      "path": "Databases/CRM/CRM.md"
    },
    {
      "basename": "Recipes",
      "path": "Templates/Recipes.md"
    },
    {
      "basename": "Weekly",
      "path": "Templates/Weekly.md"
    },
    {
      "basename": "Zettelkasten Note",
      "path": "Templates/Zettelkasten Note.md"
    },
    {
      "basename": "Daily",
      "path": "Templates/Daily.md"
    },
    {
      "basename": "CRM",
      "path": "Computed/CRM.md"
    },
    {
      "basename": "202212122239",
      "path": "202212122239.md"
    },
    {
      "basename": "Templates",
      "path": "Templates/Templates.md"
    },
    {
      "basename": "calendar",
      "path": "_tutorial/Attachments/calendar.png"
    },
    {
      "basename": "Resources",
      "path": "_PARA/Projects/Test Project/Resources.md"
    },
    {
      "basename": "Resources",
      "path": "_PARA/Projects/Test Project 2/Resources.md"
    },
    {
      "basename": "Scratchpad",
      "path": "_PARA/Projects/Test Project 2/Scratchpad.md"
    },
    {
      "basename": "Scratchpad",
      "path": "_PARA/Projects/Test Project/Scratchpad.md"
    },
    {
      "basename": "Test Project",
      "path": "_PARA/Projects/Test Project/Test Project.md"
    },
    {
      "basename": "202212090136",
      "path": "202212090136.md"
    },
    {
      "basename": "202212090137",
      "path": "202212090137.md"
    },
    {
      "basename": "202212120002",
      "path": "202212120002.md"
    },
    {
      "basename": "Test Project 2",
      "path": "_PARA/Projects/Test Project 2/Test Project 2.md"
    },
    {
      "basename": "Canvas",
      "path": "_PARA/Projects/Test Project 2/Canvas.canvas"
    },
    {
      "basename": "seinfeld the art of seduction",
      "path": "Private/Attachments/seinfeld the art of seduction.png"
    },
    {
      "basename": "2022-W51",
      "path": "Calendar/Weekly/2022-W51.md"
    },
    {
      "basename": "README",
      "path": "README.md"
    },
    {
      "basename": "Attachments",
      "path": "Attachments/Attachments.md"
    },
    {
      "basename": "The Ancient Japanese Technique That Produces Lumber Without Cutting Trees",
      "path": "Readwise/Articles Test/The Ancient Japanese Technique That Produces Lumber Without Cutting Trees.md"
    },
    {
      "basename": "Readwise",
      "path": "Readwise/Readwise.md"
    },
    {
      "basename": "2022-12-14",
      "path": "Calendar/Daily/2022-12-14.md"
    },
    {
      "basename": "Hotkeys",
      "path": "_tutorial/Hotkeys.md"
    },
    {
      "basename": "Trackers",
      "path": "Computed/Trackers.md"
    },
    {
      "basename": "To Process",
      "path": "Computed/To Process.md"
    },
    {
      "basename": "Tasks",
      "path": "Computed/Tasks.md"
    },
    {
      "basename": "_tutorial",
      "path": "_tutorial/_tutorial.md"
    },
    {
      "basename": "Kanban",
      "path": "_PARA/Projects/Test Project 2/Kanban.md"
    },
    {
      "basename": "Kanban",
      "path": "_PARA/Projects/Test Project/Kanban.md"
    },
    {
      "basename": "Kanban",
      "path": "_PARA/Archive/Archived Project/Kanban.md"
    },
    {
      "basename": "202212141113",
      "path": "Private/202212141113.md"
    },
    {
      "basename": "Secret Note",
      "path": "Private/Secret Note.md"
    },
    {
      "basename": "Scratchpad",
      "path": "Inbox/Scratchpad.md"
    },
    {
      "basename": "2022-12-11--11-59-30",
      "path": "Inbox/Smartphone Capture/2022-12-11--11-59-30.md"
    },
    {
      "basename": "2022-12-11--12-00-00",
      "path": "Inbox/Computer Capture/2022-12-11--12-00-00.md"
    },
    {
      "basename": "2022-Q4",
      "path": "Calendar/Quarterly/2022-Q4.md"
    },
    {
      "basename": "2022-12-11",
      "path": "Calendar/Daily/2022-12-11.md"
    },
    {
      "basename": "2022-12-12",
      "path": "Calendar/Daily/2022-12-12.md"
    },
    {
      "basename": "Paste URL into Selection",
      "path": "_tests/Paste URL into Selection.md"
    },
    {
      "basename": "Readwise",
      "path": "_tests/External/Readwise.md"
    }
  ],
  "omittedPaths": [],
  "maxLength": null,
  "openType": "tab"
}